.coveragerc
.gitignore
.landscape.yaml
.travis.yml
CHANGELOG.rst
CONTRIBUTING.rst
LICENSE
PEOPLE
README.rst
run_tests.sh
setup.py
tox.ini
bin/_preamble.py
bin/build_schema.py
bin/distribute_setup.py
bin/sort_wsdl.py
doc/Makefile
doc/gendoc.sh
doc/make.bat
doc/source/conf.py
doc/source/contributing.rst
doc/source/faq.rst
doc/source/history.rst
doc/source/index.rst
doc/source/migration.rst
doc/source/tests.rst
doc/source/.static/placeholder.txt
doc/source/.templates/placeholder.txt
doc/source/manual/01_highlevel.rst
doc/source/manual/02_helloworld.rst
doc/source/manual/03_types.rst
doc/source/manual/04_usermanager.rst
doc/source/manual/05-01_sqlalchemy.rst
doc/source/manual/05-02_validation.rst
doc/source/manual/05-03_django.rst
doc/source/manual/06_metadata.rst
doc/source/manual/07_t_and_p.rst
doc/source/manual/index.rst
doc/source/manual/relational.rst
doc/source/reference/application.rst
doc/source/reference/auxproc.rst
doc/source/reference/base.rst
doc/source/reference/client.rst
doc/source/reference/decorator.rst
doc/source/reference/error.rst
doc/source/reference/index.rst
doc/source/reference/interface.rst
doc/source/reference/service.rst
doc/source/reference/util.rst
doc/source/reference/model/binary.rst
doc/source/reference/model/complex.rst
doc/source/reference/model/enum.rst
doc/source/reference/model/fault.rst
doc/source/reference/model/index.rst
doc/source/reference/model/primitive.rst
doc/source/reference/model/sql.rst
doc/source/reference/protocol/base.rst
doc/source/reference/protocol/dictdoc.rst
doc/source/reference/protocol/http.rst
doc/source/reference/protocol/index.rst
doc/source/reference/protocol/json.rst
doc/source/reference/protocol/msgpack.rst
doc/source/reference/protocol/soap.rst
doc/source/reference/protocol/xml.rst
doc/source/reference/server/django.rst
doc/source/reference/server/index.rst
doc/source/reference/server/null.rst
doc/source/reference/server/pyramid.rst
doc/source/reference/server/twisted.rst
spyne.egg-info/PKG-INFO
spyne.egg-info/SOURCES.txt
spyne.egg-info/dependency_links.txt
spyne.egg-info/entry_points.txt
spyne.egg-info/not-zip-safe
spyne.egg-info/requires.txt
spyne.egg-info/top_level.txt
